levenshtein_rs-0.1.8.dist-info/METADATA
levenshtein_rs-0.1.8.dist-info/WHEEL
levenshtein_rs-0.1.8.dist-info/license_files/LICENSE
levenshtein_rs/__init__.py
levenshtein_rs/levenshtein_rs.abi3.so
levenshtein_rs-0.1.8.dist-info/RECORD
